Metadata-Version: 2.2
Name: playground-pypi-package-j
Version: 0.1.5
Summary: A playground for uploading Python packages to PyPI
Author-email: Subin Kim <sudosubin@gmail.com>
License: MIT
